[
  {
    "id":"pedro",
	  "skills": ["python","java","css"],
	  "location": "east",
	  "seniority": "senior",
	  "personality": "analyst",
    "gender": "male",
	  "sentiment_analysis": "positive" ,
	  "english_proficiency": "good"
  },
  {
    "id":"john",
	  "skills": ["c++","aws","php"],
	  "location": "west",
	  "seniority": "medium",
	  "personality": "diplomat",
    "gender": "male",
	  "sentiment_analysis": "neutral",
	  "english_proficiency": "good"
  },
  {
    "id":"allen",
	  "skills": ["javascript","docker","html"],
	  "location": "west",
	  "seniority": "senior",
	  "personality": "sentinel",
    "gender": "male",
	  "sentiment_analysis": "negative",
	  "english_proficiency": "poor"
  },
  {
    "id":"andrew",
	  "skills": ["php","c#","nodejs"],
	  "location": "east",
	  "seniority": "medium",
	  "personality": "explorer",
    "gender": "male",
	  "sentiment_analysis": "mixed",
	  "english_proficiency": "good"
  },
  {
    "id":"aaron",
	  "skills": ["django","css","aws"],
	  "location": "east",
	  "seniority": "senior",
	  "personality": "diplomat",
    "gender": "male",
	  "sentiment_analysis": "positive",
	  "english_proficiency": "good"
  },
  {
    "id":"archie",
	  "skills": ["python","aws","c++"],
	  "location": "west",
	  "seniority": "medium",
	  "personality": "analyst",
    "gender": "male",
	  "sentiment_analysis": "negative",
	  "english_proficiency": "good"
  },
  {
    "id":"brayan",
	  "skills": ["nodejs","aws","django"],
	  "location": "west",
	  "seniority": "medium",
	  "personality": "explorer",
    "gender": "male",
	  "sentiment_analysis": "neutral",
	  "english_proficiency": "good"
  },
  {
    "id":"boris",
	  "skills": ["java","docker","css"],
	  "location": "east",
	  "seniority": "medium",
	  "personality": "sentinel",
    "gender": "male",
	  "sentiment_analysis": "mixed",
	  "english_proficiency": "poor"
  },
  {
    "id":"zack",
	  "skills": ["css","php","python"],
	  "location": "east",
	  "seniority": "medium",
	  "personality": "analyst",
    "gender": "male",
	  "sentiment_analysis": "positive",
	  "english_proficiency": "good"
  },
  {
    "id":"zachary",
	  "skills": ["python","django","aws"],
	  "location": "west",
	  "seniority": "senior",
	  "personality": "diplomat",
    "gender": "male",
	  "sentiment_analysis": "mixed",
	  "english_proficiency": "poor"
  },
  {
    "id":"ulysses",
	  "skills": ["css","aws","docker"],
	  "location": "west",
	  "seniority": "medium",
	  "personality": "sentinel",
    "gender": "male",
	  "sentiment_analysis": "negative",
	  "english_proficiency": "good"
  },
  {
    "id":"nestor",
	  "skills": ["c++","html","javascript"],
	  "location": "east",
	  "seniority": "senior",
	  "personality": "explorer",
    "gender": "male",
	  "sentiment_analysis": "neutral",
	  "english_proficiency": "good"
  },
  {
    "id":"neville",
	  "skills": ["php","c#","django"],
	  "location": "west",
	  "seniority": "medium",
	  "personality": "diplomat",
    "gender": "male",
	  "sentiment_analysis": "positive",
	  "english_proficiency": "good"
  },
  {
    "id":"norberto",
	  "skills": ["python","django","docker"],
	  "location": "east",
	  "seniority": "medium",
	  "personality": "analyst",
    "gender": "male",
	  "sentiment_analysis": "neutral",
	  "english_proficiency": "good"
  },
  {
    "id":"norman",
	  "skills": ["java","javascript","nodejs"],
	  "location": "west",
	  "seniority": "medium",
	  "personality": "explorer",
    "gender": "male",
	  "sentiment_analysis": "positive",
	  "english_proficiency": "poor"
  },
  {
    "id":"lou",
	  "skills": ["aws","python","c"],
	  "location": "east",
	  "seniority": "senior",
	  "personality": "sentinel",
    "gender": "male",
	  "sentiment_analysis": "positive",
	  "english_proficiency": "good"
  },
  {
    "id":"lucius",
	  "skills": ["django","docker","c"],
	  "location": "east",
	  "seniority": "senior",
	  "personality": "analyst",
    "gender": "male",
	  "sentiment_analysis": "mixed",
	  "english_proficiency": "poor"
  },
  {
    "id":"lester",
	  "skills": ["html","c","php"],
	  "location": "east",
	  "seniority": "medium",
	  "personality": "explorer",
    "gender": "male",
	  "sentiment_analysis": "positive",
	  "english_proficiency": "good"
  },
  {
    "id":"luis",
	  "skills": ["docker","php","java"],
	  "location": "west",
	  "seniority": "medium",
	  "personality": "diplomat",
    "gender": "male",
	  "sentiment_analysis": "neutral",
	  "english_proficiency": "good"
  },
  {
    "id":"karl",
	  "skills": ["python","c#","html"],
	  "location": "west",
	  "seniority": "medium",
	  "personality": "sentinel",
    "gender": "male",
	  "sentiment_analysis": "negative",
	  "english_proficiency": "good"
  },
  {
    "id":"kyle",
	  "skills": ["php","django","docker"],
	  "location": "west",
	  "seniority": "senior",
	  "personality": "analyst",
    "gender": "male",
	  "sentiment_analysis": "positive",
	  "english_proficiency": "poor"
  },
  {
    "id":"kevin",
	  "skills": ["css","nodejs","javascript"],
	  "location": "east",
	  "seniority": "medium",
	  "personality": "explorer",
    "gender": "male",
	  "sentiment_analysis": "neutral",
	  "english_proficiency": "good"
  },
  {
    "id":"hector",
	  "skills": ["python","html","aws"],
	  "location": "west",
	  "seniority": "medium",
	  "personality": "sentinel",
    "gender": "male",
	  "sentiment_analysis": "positive",
	  "english_proficiency": "good"
  },
  {
    "id":"hunter",
	  "skills": ["docker","css","c#"],
	  "location": "east",
	  "seniority": "medium",
	  "personality": "explorer",
    "gender": "male",
	  "sentiment_analysis": "neutral",
	  "english_proficiency": "good"
  },
  {
    "id":"fletcher",
	  "skills": ["php","django","c#"],
	  "location": "west",
	  "seniority": "senior",
	  "personality": "analyst",
    "gender": "male",
	  "sentiment_analysis": "neutral",
	  "english_proficiency": "good"
  },
  {
    "id":"fernando",
	  "skills": ["docker","aws","html"],
	  "location": "east",
	  "seniority": "medium",
	  "personality": "analyst",
    "gender": "male",
	  "sentiment_analysis": "mixed",
	  "english_proficiency": "poor"
  },
  {
    "id":"Carla",
	  "skills": ["python","java","c"],
	  "location": "west",
	  "seniority": "medium",
	  "personality": "analyst",
    "gender": "female",
	  "sentiment_analysis": "positive" ,
	  "english_proficiency": "poor"
  },
  {
    "id":"Louis",
	  "skills": ["nodejs","Django","java"],
	  "location": ["west"],
	  "seniority": ["senior"],
	  "personality": ["diplomat"],
    "gender": ["female"],
	  "sentiment_analysis": ["negative"],
	  "english_proficiency": ["good"]
  },
  {
    "id":"linda",
	  "skills": ["python","docker","aws"],
	  "location": ["east"],
	  "seniority": ["medium"],
	  "personality": ["sentinel"],
    "gender": ["female"],
	  "sentiment_analysis": ["neutral"],
	  "english_proficiency": ["good"]
  },
  {
    "id":"natasha",
	  "skills": ["html","php","java"],
	  "location": ["west"],
	  "seniority": ["senior"],
	  "personality": ["explorer"],
    "gender": ["female"],
	  "sentiment_analysis": ["mixed"],
	  "english_proficiency": ["poor"]
  },
  {
    "id":"caroline",
	  "skills": ["nodejs","c#","c++"],
	  "location": ["west"],
	  "seniority": ["medium"],
	  "personality": ["analyst"],
    "gender": ["female"],
	  "sentiment_analysis": ["positive"],
	  "english_proficiency": ["good"]
  },
  {
    "id":"maria",
	  "skills": ["python","c","html"],
	  "location": ["east"],
	  "seniority": ["senior"],
	  "personality": ["diplomat"],
    "gender": ["female"],
	  "sentiment_analysis": ["positive"],
	  "english_proficiency": ["good"]
  },
  {
    "id":"christine",
	  "skills": ["javascript","nodejs","django"],
	  "location": ["east"],
	  "seniority": ["medium"],
	  "personality": ["sentinel"],
    "gender": ["female"],
	  "sentiment_analysis": ["negative"],
	  "english_proficiency": ["poor"]
  },
  {
    "id":"lucia",
	  "skills": ["php","c#","java"],
	  "location": ["west"],
	  "seniority": ["medium"],
	  "personality": ["explorer"],
    "gender": ["female"],
	  "sentiment_analysis": ["neutral"],
	  "english_proficiency": ["poor"]
  },
  {
    "id":"camila",
	  "skills": ["javascript","docker","aws"],
	  "location": ["west"],
	  "seniority": ["medium"],
	  "personality": ["analyst"],
    "gender": ["female"],
	  "sentiment_analysis": ["mixed"],
	  "english_proficiency": ["good"]
  },
  {
    "id":"estefany",
	  "skills": ["php","python","c#"],
	  "location": ["east"],
	  "seniority": ["medium"],
	  "personality": ["diplomat"],
    "gender": ["female"],
	  "sentiment_analysis": ["positive"],
	  "english_proficiency": ["poor"]
  },
  {
    "id":"tania",
	  "skills": ["c#","c++","c"],
	  "location": ["west"],
	  "seniority": ["medium"],
	  "personality": ["sentinel"],
    "gender": ["female"],
	  "sentiment_analysis": ["negative"],
	  "english_proficiency": ["good"]
  },
  {
    "id":"sabrina",
	  "skills": ["javascript","php","css"],
	  "location": ["west"],
	  "seniority": ["senior"],
	  "personality": ["explorer"],
    "gender": ["female"],
	  "sentiment_analysis": ["negative"],
	  "english_proficiency": ["good"]
  },
  {
    "id":"flavia",
	  "skills": ["django","python","html"],
	  "location": ["east"],
	  "seniority": ["senior"],
	  "personality": ["analyst"],
    "gender": ["female"],
	  "sentiment_analysis": ["neutral"],
	  "english_proficiency": ["poor"]
  },
  {
    "id":"megan",
	  "skills": ["java","python","docker"],
	  "location": ["west"],
	  "seniority": ["medium"],
	  "personality": ["diplomat"],
    "gender": ["female"],
	  "sentiment_analysis": ["mixed"],
	  "english_proficiency": ["good"]
  },
  {
    "id":"Laura",
	  "skills": ["aws","java","c#"],
	  "location": ["west"],
	  "seniority": ["medium"],
	  "personality": ["sentinel"],
    "gender": ["female"],
	  "sentiment_analysis": ["positive"],
	  "english_proficiency": ["good"]
  },
  {
    "id":"paola",
	  "skills": ["java","php","c"],
	  "location": ["east"],
	  "seniority": ["senior"],
	  "personality": ["explorer"],
    "gender": ["female"],
	  "sentiment_analysis": ["negative"],
	  "english_proficiency": ["good"]
  },
  {
    "id":"amanda",
	  "skills": ["java","css","aws"],
	  "location": ["east"],
	  "seniority": ["medium"],
	  "personality": ["analyst"],
    "gender": ["female"],
	  "sentiment_analysis": ["neutral"],
	  "english_proficiency": ["poor"]
  },
  {
    "id":"erika",
	  "skills": ["javascript","python","docker"],
	  "location": ["west"],
	  "seniority": ["senior"],
	  "personality": ["diplomat"],
    "gender": ["female"],
	  "sentiment_analysis": ["mixed"],
	  "english_proficiency": ["good"]
  },
  {
    "id":"jennifer",
	  "skills": ["php","c#","c++"],
	  "location": ["east"],
	  "seniority": ["medium"],
	  "personality": ["sentinel"],
    "gender": ["female"],
	  "sentiment_analysis": ["positive"],
	  "english_proficiency": ["good"]
  },
  {
    "id":"martina",
	  "skills": ["python","nodejs","c"],
	  "location": ["west"],
	  "seniority": ["senior"],
	  "personality": ["explorer"],
    "gender": ["female"],
	  "sentiment_analysis": ["negative"],
	  "english_proficiency": ["poor"]
  },
{
    "id":"miriam",
	  "skills": ["nodejs","c#","php"],
	  "location": ["west"],
	  "seniority": ["medium"],
	  "personality": ["analyst"],
    "gender": ["female"],
	  "sentiment_analysis": ["neutral"],
	  "english_proficiency": ["good"]
  },
{
    "id":"luciana",
	  "skills": ["java","aws","html"],
	  "location": ["east"],
	  "seniority": ["senior"],
	  "personality": ["analyst"],
    "gender": ["female"],
	  "sentiment_analysis": ["mixed"],
	  "english_proficiency": ["poor"]
  },
{
    "id":"karina",
	  "skills": ["python","aws","docker"],
	  "location": ["west"],
	  "seniority": ["medium"],
	  "personality": ["diplomat"],
    "gender": ["female"],
	  "sentiment_analysis": ["positive"],
	  "english_proficiency": ["good"]
  },
{
    "id":"eli",
	  "skills": ["javascript","css","php"],
	  "location": ["east"],
	  "seniority": ["senior"],
	  "personality": ["sentinel"],
    "gender": ["female"],
	  "sentiment_analysis": ["negative"],
	  "english_proficiency": ["good"]
  },
  {
    "id":"Gal",
	  "skills": ["php","aws","python"],
	  "location":["west"],
	  "seniority": ["senior"],
	  "personality": ["sentinel"],
    "gender": ["female"],
	  "sentiment_analysis": ["mixed"],
	  "english_proficiency": ["good"]
  }
]
